Daystar/__init__.py
Daystar-1.0.1.dist-info/LICENSE
Daystar-1.0.1.dist-info/METADATA
Daystar-1.0.1.dist-info/WHEEL
Daystar-1.0.1.dist-info/top_level.txt
Daystar-1.0.1.dist-info/RECORD
