Metadata-Version: 2.1
Name: Daystar
Version: 1.0.1
Summary: Solar calculation class for Python
Author: Siddhu Pendyala
Author-email: siddhu.pendyala@outlook.com
Classifier: Programming Language :: Python :: 3
Classifier: License :: OSI Approved :: MIT License
Classifier: Operating System :: OS Independent
Requires-Python: >=3.6
License-File: LICENSE
Requires-Dist: Solarflare
